mathlikeanim_rs/__init__.py
mathlikeanim_rs/gradient_image_or_color.py
mathlikeanim_rs/node_modules/.package-lock.json
mathlikeanim_rs/node_modules/mathlikeanim-rs/index.d.ts
mathlikeanim_rs/node_modules/mathlikeanim-rs/index.js
mathlikeanim_rs/node_modules/mathlikeanim-rs/index_bg.wasm
mathlikeanim_rs/node_modules/mathlikeanim-rs/LICENSE
mathlikeanim_rs/node_modules/mathlikeanim-rs/package.json
mathlikeanim_rs/node_modules/mathlikeanim-rs/README.md
mathlikeanim_rs/package-lock.json
mathlikeanim_rs/package.json
mathlikeanim_rs/scene.js
mathlikeanim_rs/scene.py
mathlikeanim_rs/three_d_object.py
mathlikeanim_rs/utils.py
mathlikeanim_rs/vector_object.py
mathlikeanim_rs-0.13.27.dist-info/METADATA
mathlikeanim_rs-0.13.27.dist-info/WHEEL
mathlikeanim_rs-0.13.27.dist-info/RECORD
