Metadata-Version: 2.1
Name: mathlikeanim-rs
Version: 0.13.27
Summary: A Rust library for creating mathematical animations, now in Python
Home-page: https://github.com/MathItYT/mathlikeanim-rs
Author: MathItYT
Author-email: benjamin.ubilla@uc.cl
Requires-Python: >=3.11,<3.14
Classifier: Programming Language :: Python :: 3
Classifier: Programming Language :: Python :: 3.11
Classifier: Programming Language :: Python :: 3.12
Classifier: Programming Language :: Python :: 3.13
Requires-Dist: nicegui (>=2.9.0,<3.0.0)
Project-URL: Repository, https://github.com/MathItYT/mathlikeanim-rs
